pyqentangle/__init__.py
pyqentangle/continuous.py
pyqentangle/metrics.py
pyqentangle/schmidt.py
pyqentangle/tncompute.py
pyqentangle/utils.py
pyqentangle/quantumstates/__init__.py
pyqentangle/quantumstates/bipartite.py
pyqentangle/quantumstates/harmonics.py
pyqentangle-4.0.4.dist-info/LICENSE
pyqentangle-4.0.4.dist-info/METADATA
pyqentangle-4.0.4.dist-info/WHEEL
pyqentangle-4.0.4.dist-info/top_level.txt
pyqentangle-4.0.4.dist-info/RECORD
