Metadata-Version: 2.1
Name: pyqentangle
Version: 4.0.4
Summary: Quantum Entanglement in Python
Author-email: Kwan Yuet Stephen Ho <stephenhky@yahoo.com.hk>
License: MIT
Project-URL: Documentation, http://pyqentangle.readthedocs.io
Project-URL: Repository, https://github.com/stephenhky/pyqentangle
Project-URL: Issues, https://github.com/stephenhky/pyqentangle/issues
Keywords: quantum physics,quantum information,Schmidt decomposition,entanglement
Classifier: Topic :: Scientific/Engineering :: Physics
Classifier: Topic :: Scientific/Engineering :: Mathematics
Classifier: Topic :: Scientific/Engineering :: Chemistry
Classifier: License :: OSI Approved :: MIT License
Classifier: Programming Language :: Python :: 3.7
Classifier: Programming Language :: Python :: 3.8
Classifier: Programming Language :: Python :: 3.9
Classifier: Programming Language :: Python :: 3.10
Classifier: Programming Language :: Python :: 3.11
Classifier: Programming Language :: Python :: 3.12
Classifier: Programming Language :: Python :: 3.13
Classifier: Intended Audience :: Science/Research
Classifier: Intended Audience :: Developers
Classifier: Intended Audience :: Education
Requires-Python: >=3.7
License-File: LICENSE
Requires-Dist: numpy>=1.20.0
Requires-Dist: scipy>=1.4.0
Requires-Dist: tensornetwork>=0.4.0
Provides-Extra: test
Requires-Dist: unittest2; extra == "test"
Requires-Dist: pytest; extra == "test"
